<annotation>
	<folder>avocado_output</folder>
	<filename>b7e9a2cad530fda43ba8627e5248a49cfe-25-avocados.rsquare.w1200.jpg</filename>
	<path>/home/jayden/Desktop/Self_Learning/Object_Detection/data_set/avocado_output/b7e9a2cad530fda43ba8627e5248a49cfe-25-avocados.rsquare.w1200.jpg</path>
	<source>
		<database>Unknown</database>
	</source>
	<size>
		<width>1200</width>
		<height>1200</height>
		<depth>3</depth>
	</size>
	<segmented>0</segmented>
	<object>
		<name>ripe</name>
		<pose>Unspecified</pose>
		<truncated>0</truncated>
		<difficult>0</difficult>
		<bndbox>
			<xmin>593</xmin>
			<ymin>794</ymin>
			<xmax>899</xmax>
			<ymax>1158</ymax>
		</bndbox>
	</object>
	<object>
		<name>ripe</name>
		<pose>Unspecified</pose>
		<truncated>0</truncated>
		<difficult>0</difficult>
		<bndbox>
			<xmin>902</xmin>
			<ymin>787</ymin>
			<xmax>1197</xmax>
			<ymax>1141</ymax>
		</bndbox>
	</object>
	<object>
		<name>ripe</name>
		<pose>Unspecified</pose>
		<truncated>0</truncated>
		<difficult>0</difficult>
		<bndbox>
			<xmin>757</xmin>
			<ymin>543</ymin>
			<xmax>1065</xmax>
			<ymax>878</ymax>
		</bndbox>
	</object>
	<object>
		<name>ripe</name>
		<pose>Unspecified</pose>
		<truncated>1</truncated>
		<difficult>0</difficult>
		<bndbox>
			<xmin>996</xmin>
			<ymin>1</ymin>
			<xmax>1200</xmax>
			<ymax>173</ymax>
		</bndbox>
	</object>
	<object>
		<name>almost</name>
		<pose>Unspecified</pose>
		<truncated>0</truncated>
		<difficult>0</difficult>
		<bndbox>
			<xmin>590</xmin>
			<ymin>284</ymin>
			<xmax>906</xmax>
			<ymax>599</ymax>
		</bndbox>
	</object>
	<object>
		<name>almost</name>
		<pose>Unspecified</pose>
		<truncated>1</truncated>
		<difficult>0</difficult>
		<bndbox>
			<xmin>915</xmin>
			<ymin>293</ymin>
			<xmax>1200</xmax>
			<ymax>592</ymax>
		</bndbox>
	</object>
	<object>
		<name>almost</name>
		<pose>Unspecified</pose>
		<truncated>1</truncated>
		<difficult>0</difficult>
		<bndbox>
			<xmin>1</xmin>
			<ymin>276</ymin>
			<xmax>266</xmax>
			<ymax>593</ymax>
		</bndbox>
	</object>
	<object>
		<name>almost</name>
		<pose>Unspecified</pose>
		<truncated>1</truncated>
		<difficult>0</difficult>
		<bndbox>
			<xmin>494</xmin>
			<ymin>1</ymin>
			<xmax>746</xmax>
			<ymax>224</ymax>
		</bndbox>
	</object>
	<object>
		<name>almost</name>
		<pose>Unspecified</pose>
		<truncated>0</truncated>
		<difficult>0</difficult>
		<bndbox>
			<xmin>747</xmin>
			<ymin>28</ymin>
			<xmax>992</xmax>
			<ymax>277</ymax>
		</bndbox>
	</object>
	<object>
		<name>almost</name>
		<pose>Unspecified</pose>
		<truncated>1</truncated>
		<difficult>0</difficult>
		<bndbox>
			<xmin>1</xmin>
			<ymin>27</ymin>
			<xmax>252</xmax>
			<ymax>249</ymax>
		</bndbox>
	</object>
	<object>
		<name>almost</name>
		<pose>Unspecified</pose>
		<truncated>1</truncated>
		<difficult>0</difficult>
		<bndbox>
			<xmin>1</xmin>
			<ymin>834</ymin>
			<xmax>254</xmax>
			<ymax>1167</ymax>
		</bndbox>
	</object>
	<object>
		<name>unripe</name>
		<pose>Unspecified</pose>
		<truncated>0</truncated>
		<difficult>0</difficult>
		<bndbox>
			<xmin>236</xmin>
			<ymin>3</ymin>
			<xmax>494</xmax>
			<ymax>232</ymax>
		</bndbox>
	</object>
	<object>
		<name>unripe</name>
		<pose>Unspecified</pose>
		<truncated>0</truncated>
		<difficult>0</difficult>
		<bndbox>
			<xmin>365</xmin>
			<ymin>187</ymin>
			<xmax>621</xmax>
			<ymax>387</ymax>
		</bndbox>
	</object>
	<object>
		<name>unripe</name>
		<pose>Unspecified</pose>
		<truncated>0</truncated>
		<difficult>0</difficult>
		<bndbox>
			<xmin>147</xmin>
			<ymin>219</ymin>
			<xmax>357</xmax>
			<ymax>382</ymax>
		</bndbox>
	</object>
	<object>
		<name>unripe</name>
		<pose>Unspecified</pose>
		<truncated>0</truncated>
		<difficult>0</difficult>
		<bndbox>
			<xmin>249</xmin>
			<ymin>292</ymin>
			<xmax>590</xmax>
			<ymax>609</ymax>
		</bndbox>
	</object>
	<object>
		<name>unripe</name>
		<pose>Unspecified</pose>
		<truncated>0</truncated>
		<difficult>0</difficult>
		<bndbox>
			<xmin>82</xmin>
			<ymin>563</ymin>
			<xmax>400</xmax>
			<ymax>894</ymax>
		</bndbox>
	</object>
	<object>
		<name>unripe</name>
		<pose>Unspecified</pose>
		<truncated>0</truncated>
		<difficult>0</difficult>
		<bndbox>
			<xmin>417</xmin>
			<ymin>557</ymin>
			<xmax>745</xmax>
			<ymax>863</ymax>
		</bndbox>
	</object>
	<object>
		<name>unripe</name>
		<pose>Unspecified</pose>
		<truncated>0</truncated>
		<difficult>0</difficult>
		<bndbox>
			<xmin>256</xmin>
			<ymin>819</ymin>
			<xmax>589</xmax>
			<ymax>1163</ymax>
		</bndbox>
	</object>
	<object>
		<name>ripe</name>
		<pose>Unspecified</pose>
		<truncated>1</truncated>
		<difficult>0</difficult>
		<bndbox>
			<xmin>1047</xmin>
			<ymin>73</ymin>
			<xmax>1200</xmax>
			<ymax>310</ymax>
		</bndbox>
	</object>
</annotation>
