<annotation>
	<folder>Object_Detection</folder>
	<filename>lugiahooh-184727.jpeg</filename>
	<path>/home/jayden/Desktop/Self_Learning/Object_Detection/lugiahooh-184727.jpeg</path>
	<source>
		<database>Unknown</database>
	</source>
	<size>
		<width>655</width>
		<height>368</height>
		<depth>3</depth>
	</size>
	<segmented>0</segmented>
	<object>
		<name>lugia</name>
		<pose>Unspecified</pose>
		<truncated>0</truncated>
		<difficult>0</difficult>
		<bndbox>
			<xmin>359</xmin>
			<ymin>126</ymin>
			<xmax>423</xmax>
			<ymax>187</ymax>
		</bndbox>
	</object>
</annotation>
